llama_index/retrievers/superlinked/__init__.py
llama_index/retrievers/superlinked/retriever.py
llama_index_retrievers_superlinked-0.1.2.dist-info/METADATA
llama_index_retrievers_superlinked-0.1.2.dist-info/WHEEL
llama_index_retrievers_superlinked-0.1.2.dist-info/licenses/LICENSE
llama_index_retrievers_superlinked-0.1.2.dist-info/RECORD
