Metadata-Version: 2.4
Name: llama-index-retrievers-superlinked
Version: 0.1.2
Summary: LlamaIndex retriever integration for Superlinked
Project-URL: Homepage, https://github.com/run-llama/llama_index
Author-email: Superlinked <dev@superlinked.com>
License: MIT
License-File: LICENSE
Classifier: License :: OSI Approved :: MIT License
Classifier: Operating System :: OS Independent
Classifier: Programming Language :: Python :: 3
Requires-Python: <4.0,>=3.10
Requires-Dist: llama-index-core<0.14,>=0.13.1
Requires-Dist: pandas<3.0.0,>=2.2.0
Requires-Dist: superlinked==33.5.1
